{"derived_from":[],"hm_receipt":null,"output":{"base_L0":{"t":"bytes","v":"hex:666666666666ee3f"},"base_L1":{"t":"bytes","v":"hex:000000000000f03f"},"base_L2":{"t":"bytes","v":"hex:000000000000f03f"},"base_L3":{"t":"bytes","v":"hex:5c8fc2f5285cef3f"},"base_L4":{"t":"bytes","v":"hex:5c8fc2f5285cef3f"},"base_L5":{"t":"bytes","v":"hex:0ad7a3703d0aef3f"},"base_L6":{"t":"bytes","v":"hex:5c8fc2f5285cef3f"},"localized_z0":0,"localized_z1":0,"localized_z2":0,"localized_z3":0,"localized_z4":0,"localized_z5":0,"localized_z6":0,"n_samples":100,"t":"causal_intervention_certified","z0_L0":{"t":"bytes","v":"hex:666666666666ee3f"},"z0_L1":{"t":"bytes","v":"hex:000000000000f03f"},"z0_L2":{"t":"bytes","v":"hex:000000000000f03f"},"z0_L3":{"t":"bytes","v":"hex:5c8fc2f5285cef3f"},"z0_L4":{"t":"bytes","v":"hex:5c8fc2f5285cef3f"},"z0_L5":{"t":"bytes","v":"hex:0ad7a3703d0aef3f"},"z0_L6":{"t":"bytes","v":"hex:5c8fc2f5285cef3f"},"z1_L0":{"t":"bytes","v":"hex:666666666666ee3f"},"z1_L1":{"t":"bytes","v":"hex:7b14ae47e17a843f"},"z1_L2":{"t":"bytes","v":"hex:0000000000000000"},"z1_L3":{"t":"bytes","v":"hex:0000000000000000"},"z1_L4":{"t":"bytes","v":"hex:7b14ae47e17aa43f"},"z1_L5":{"t":"bytes","v":"hex:7b14ae47e17a843f"},"z1_L6":{"t":"bytes","v":"hex:0000000000000000"},"z2_L0":{"t":"bytes","v":"hex:666666666666ee3f"},"z2_L1":{"t":"bytes","v":"hex:000000000000f03f"},"z2_L2":{"t":"bytes","v":"hex:7b14ae47e17a943f"},"z2_L3":{"t":"bytes","v":"hex:0000000000000000"},"z2_L4":{"t":"bytes","v":"hex:7b14ae47e17aa43f"},"z2_L5":{"t":"bytes","v":"hex:0000000000000000"},"z2_L6":{"t":"bytes","v":"hex:7b14ae47e17a843f"},"z3_L0":{"t":"bytes","v":"hex:666666666666ee3f"},"z3_L1":{"t":"bytes","v":"hex:000000000000f03f"},"z3_L2":{"t":"bytes","v":"hex:000000000000f03f"},"z3_L3":{"t":"bytes","v":"hex:0000000000000000"},"z3_L4":{"t":"bytes","v":"hex:b81e85eb51b89e3f"},"z3_L5":{"t":"bytes","v":"hex:7b14ae47e17a943f"},"z3_L6":{"t":"bytes","v":"hex:7b14ae47e17a843f"},"z4_L0":{"t":"bytes","v":"hex:666666666666ee3f"},"z4_L1":{"t":"bytes","v":"hex:000000000000f03f"},"z4_L2":{"t":"bytes","v":"hex:000000000000f03f"},"z4_L3":{"t":"bytes","v":"hex:5c8fc2f5285cef3f"},"z4_L4":{"t":"bytes","v":"hex:7b14ae47e17a843f"},"z4_L5":{"t":"bytes","v":"hex:0000000000000000"},"z4_L6":{"t":"bytes","v":"hex:7b14ae47e17a843f"},"z5_L0":{"t":"bytes","v":"hex:666666666666ee3f"},"z5_L1":{"t":"bytes","v":"hex:000000000000f03f"},"z5_L2":{"t":"bytes","v":"hex:000000000000f03f"},"z5_L3":{"t":"bytes","v":"hex:5c8fc2f5285cef3f"},"z5_L4":{"t":"bytes","v":"hex:5c8fc2f5285cef3f"},"z5_L5":{"t":"bytes","v":"hex:0000000000000000"},"z5_L6":{"t":"bytes","v":"hex:0000000000000000"},"z6_L0":{"t":"bytes","v":"hex:666666666666ee3f"},"z6_L1":{"t":"bytes","v":"hex:000000000000f03f"},"z6_L2":{"t":"bytes","v":"hex:000000000000f03f"},"z6_L3":{"t":"bytes","v":"hex:5c8fc2f5285cef3f"},"z6_L4":{"t":"bytes","v":"hex:5c8fc2f5285cef3f"},"z6_L5":{"t":"bytes","v":"hex:0ad7a3703d0aef3f"},"z6_L6":{"t":"bytes","v":"hex:0000000000000000"}},"run_id":"sha256:2d34004dcf4847d45d04218bbefc2c9d3bdf3d0946269a579cfd318d583606fd"}